{"createdAt":"2024-12-26T00:23:06.866Z","updatedAt":"2024-12-26T01:56:06.000Z","id":"Yu3TF2XMLFEjEsho","name":"\b주요 워크플로우 모음","active":false,"nodes":[{"parameters":{},"id":"5ca4368a-3e6e-4c95-bbde-de1e08aae9fb","name":"When clicking ‘Test workflow’","type":"n8n-nodes-base.manualTrigger","typeVersion":1,"position":[780,780]},{"parameters":{"jsCode":"const input = $input.all()\nlet items = [];\nfor (const item of input) {\n  items.push({   \n    \"from\": \"028876749\",\n    \"to\": item.json['phoneKey'],\n    \"text\": item.json['content'],\n    \"subject\": item.json['title']\n  });\n}\n\nreturn {\n  messages: items\n}"},"id":"159bc637-3bd3-46e7-af84-3039bf3a34ef","name":"Code","type":"n8n-nodes-base.code","typeVersion":2,"position":[820,-560]},{"parameters":{"method":"POST","url":"={{ $vars.gpters_internal_api_endpoint }}/solapi","sendHeaders":true,"headerParameters":{"parameters":[{"name":"={{ $vars.gpters_internal_api_token_key}}","value":"={{ $vars.gpters_internal_api_token }}"}]},"sendBody":true,"bodyParameters":{"parameters":[{"name":"input","value":"={ \"messages\": {{ JSON.stringify($json.messages) }} }"}]},"options":{}},"id":"78e4dc4e-391f-43c3-bc0f-bff9d61f8aec","name":"HTTP Request1","type":"n8n-nodes-base.httpRequest","typeVersion":4.2,"position":[1040,-560]},{"parameters":{"content":"## 문자 발송 FLOW","height":416,"width":401},"id":"b8f45d65-2766-4b42-b316-f7a9dc434d45","name":"Sticky Note","type":"n8n-nodes-base.stickyNote","typeVersion":1,"position":[780,-720]},{"parameters":{"assignments":{"assignments":[{"id":"4b7997f6-c3ce-43ed-a1e0-a4e4441ac59c","name":"text","value":"={{ $('Edit Fields1').all().length }}명에게 문자 발송 되었습니다.","type":"string"}]},"options":{}},"id":"5481c594-fbe6-4b6a-a280-6bcc57ecfde9","name":"Edit Fields2","type":"n8n-nodes-base.set","typeVersion":3.4,"position":[820,140],"executeOnce":true},{"parameters":{"workflowId":{"__rl":true,"value":"XVWUaUPaaiGofxQ6","mode":"list","cachedResultName":"GPTers — slackNoti_airtable"},"options":{}},"id":"00d6bf09-9a72-4f57-a439-41a867035beb","name":"Execute Workflow1","type":"n8n-nodes-base.executeWorkflow","typeVersion":1.1,"position":[1240,140],"executeOnce":true},{"parameters":{"content":"## 발송 내역을 에어테이블에 발송하는 workflow","height":319,"width":654},"id":"f57233eb-c969-4676-966f-98ad2040646e","name":"Sticky Note1","type":"n8n-nodes-base.stickyNote","typeVersion":1,"position":[780,0]},{"parameters":{"method":"POST","url":"={{ $vars.gpters_internal_api_endpoint }}/emails","sendHeaders":true,"headerParameters":{"parameters":[{"name":"={{ $vars.gpters_internal_api_token_key }}","value":"={{ $vars.gpters_internal_api_token }}"}]},"sendBody":true,"bodyParameters":{"parameters":[{"name":"content","value":"={{ $json.content }}"},{"name":"preview","value":"={{ $json.preview }}"},{"name":"bcc","value":"={{ [JSON.stringify($json.email) ]}}"},{"name":"title","value":"={{ $json.title }}"},{"name":"transactionId","value":"={{ $json.transactionId }}"},{"name":"=emailId","value":"={{ $json.emailId }}"}]},"options":{"batching":{"batch":{"batchSize":10,"batchInterval":10000}}}},"id":"98bcfcea-2017-4455-b358-e1563f174abc","name":"HTTP Request","type":"n8n-nodes-base.httpRequest","typeVersion":4.2,"position":[1320,-220],"retryOnFail":true,"maxTries":5,"waitBetweenTries":5000,"onError":"continueRegularOutput","notes":"### 7. HTTP Request\n- **설명**: 준비된 이메일 콘텐츠를 지정된 API로 전송합니다.\n- **기능**: 설정된 API 엔드포인트로 이메일을 POST 요청으로 전송합니다. 실패 시 최대 5회 재시도하며, 성공 시 알림을 전송합니다."},{"parameters":{"jsCode":"// Edit Fields1 노드의 모든 출력 데이터 가져오기\nconst editFields1Data = $('sendEmail').all();\n\n// Edit Fields7 노드의 모든 출력 데이터 가져오기\nconst editFields7Data = $('Edit Fields7').all();\n\n// 두 배열의 길이가 같다고 가정\n// editFields1Data[i].json, editFields7Data[i].json 을 하나의 객체로 합침\nconst combinedData = editFields1Data.map((item, index) => {\n  return {\n    ...item.json,\n    ...editFields7Data[index].json\n  };\n});\n\n// n8n Function 노드에서는 { json: {...} } 형태의 객체 배열을 반환\nreturn combinedData.map(data => ({ json: data }));\n"},"id":"4ccf693a-b30d-45d5-ba3b-2dfba27ef304","name":"Code1","type":"n8n-nodes-base.code","typeVersion":2,"position":[1040,-220]},{"parameters":{"content":"## 이메일 발송","height":253.75,"width":751.71875},"id":"cdc40a2d-bc6d-4654-a1c7-0b1dcdebb417","name":"Sticky Note2","type":"n8n-nodes-base.stickyNote","typeVersion":1,"position":[780,-280]},{"parameters":{"operation":"search","base":{"__rl":true,"value":"={{ $('Webhook').item.json.body.table.url }}","mode":"url"},"table":{"__rl":true,"value":"={{ $('Webhook').item.json.body.table.id }}","mode":"id"},"options":{"view":{"__rl":true,"value":"={{ $('Webhook').item.json.body.view.id }}","mode":"id"}}},"id":"d84364bd-8a7b-4333-837b-4abf6ee0d2cb","name":"Airtable","type":"n8n-nodes-base.airtable","typeVersion":2.1,"position":[2140,300],"credentials":{"airtableTokenApi":{"id":"v6sNKykfBVnEaT0g","name":"Airtable Personal Access Token account"}},"notes":"### 2. Airtable\n- **설명**: Airtable에서 이메일 관련 정보를 조회합니다.\n- **기능**: 지정된 URL과 테이블 ID를 통해 데이터를 검색하여 필요한 정보를 불러옵니다."},{"parameters":{"assignments":{"assignments":[{"id":"4cd99135-3d13-4ccb-b3ac-a51e82d818f7","name":"text","value":"=VIEW : *{{ $('Webhook').item.json.body.view.name }}*\n---\nTITLE : {{ $('Webhook').item.json.body.title }}\n---\n컨텐츠 : \n```{{ $('Webhook').item.json.body.content }}\n```\n---\n\n옵션으로 5분뒤 이메일 발송 시작!\n\n취소하고 싶다면 : [링크에서STOP](https://geniefy.app.n8n.cloud/executions)","type":"string"}]},"options":{}},"id":"f0aa430e-6d93-4519-b683-3f93dd3992d7","name":"Edit Fields1","type":"n8n-nodes-base.set","typeVersion":3.4,"position":[1700,680]},{"parameters":{"unit":"minutes"},"id":"82834b90-317c-45db-8e95-7ee20a7b0ad5","name":"Wait","type":"n8n-nodes-base.wait","typeVersion":1.1,"position":[2020,680],"webhookId":"8106ed31-be61-42c6-b641-174d1d74b129"},{"parameters":{"content":"## VIEW 데이터를 가져오기","height":322.43023255813955,"width":322.54651162790697},"id":"2fbcfa7b-06a6-4ee8-84ea-eb737c8fc4ef","name":"Sticky Note5","type":"n8n-nodes-base.stickyNote","typeVersion":1,"position":[2000,160]},{"parameters":{"workflowId":{"__rl":true,"value":"XVWUaUPaaiGofxQ6","mode":"list","cachedResultName":"GPTers — slackNoti_airtable"},"mode":"each","options":{}},"id":"7fee8152-aebb-44be-b7f0-8fbe4feef8c3","name":"Execute Workflow","type":"n8n-nodes-base.executeWorkflow","typeVersion":1.1,"position":[1860,680],"executeOnce":true},{"parameters":{"content":"## VIEW 이름에 test가 없는 경우엔 5분 대기","height":272.0000000000003,"width":492.6511627906974},"id":"9e9e3001-2b0e-4013-9364-80e782fd1973","name":"Sticky Note3","type":"n8n-nodes-base.stickyNote","typeVersion":1,"position":[1660,580]},{"parameters":{"assignments":{"assignments":[{"id":"aa1c2d8d-0669-456d-83c2-e7af66846f18","name":"url","value":"={{ $('getSharedScreenUrls').item.json.download_url }}","type":"string"},{"id":"0bc88c9d-d653-407b-9b3e-8ea1072c5b9a","name":"title","value":"={{ $('Execute Workflow Trigger').first().json.start_time.slice(0,10) }} | {{ $('Execute Workflow Trigger').first().json.topic }}","type":"string"},{"id":"cad802b4-5e17-4549-8c8a-135db11e4649","name":"description","value":"={{ $('Execute Workflow Trigger').first().json.start_time }}","type":"string"},{"id":"dda21dc1-36be-4345-98ee-f9126deb9922","name":"id","value":"={{ $('Execute Workflow Trigger').item.json.id }}","type":"string"},{"id":"5622c177-e04d-4434-a43f-c0a14a8a4c1c","name":"formated Date","value":"={{ $('Execute Workflow Trigger').first().json.start_time.slice(0,10) }}","type":"string"},{"id":"9534e5fd-1861-4669-891a-85194d7222b2","name":"주제명","value":"={{ $('Execute Workflow Trigger').first().json.topic }}","type":"string"}]},"options":{}},"id":"2d1ac910-046b-4cd8-b42a-2536dd539f0a","name":"getZoomUrl","type":"n8n-nodes-base.set","typeVersion":3.4,"position":[1060,540]},{"parameters":{"method":"POST","url":"https://hooks.zapier.com/hooks/catch/16062411/2tpqe2r/","sendBody":true,"bodyParameters":{"parameters":[{"name":"title","value":"={{ $json.title }}"},{"name":"url","value":"={{ $json.url }}"},{"name":"description","value":"={{ $json.description }}"},{"name":"id","value":"={{ $json.id }}"},{"name":"주제명","value":"={{ $json.주제명 }}"},{"name":"Formated Date","value":"={{ $json['formated Date'] }}"}]},"options":{}},"id":"af2a6985-8a99-4752-8a6d-9ecbede96f8c","name":"sendHookZapier","type":"n8n-nodes-base.httpRequest","typeVersion":4.2,"position":[1280,540]},{"parameters":{"content":"## 유튜브 업로드 ","height":390.46875,"width":732.1875},"id":"edc89731-fd58-4455-b680-545b3b3e06ea","name":"Sticky Note4","type":"n8n-nodes-base.stickyNote","typeVersion":1,"position":[780,340]},{"parameters":{"options":{}},"id":"8f7c15b0-7759-4351-890e-371dfabde922","name":"Edit Fields3","type":"n8n-nodes-base.set","typeVersion":3.4,"position":[1860,-420]},{"parameters":{"schema":{"__rl":true,"value":"public","mode":"list","cachedResultName":"public"},"table":{"__rl":true,"value":"UserCoupon","mode":"list","cachedResultName":"UserCoupon"},"columns":{"mappingMode":"defineBelow","value":{"userId":"={{ $json.id }}","issuedBy":"Admin","couponId":43293},"matchingColumns":["id"],"schema":[{"id":"id","displayName":"id","required":false,"defaultMatch":true,"display":true,"type":"number","canBeUsedToMatch":true,"removed":true},{"id":"userId","displayName":"userId","required":false,"defaultMatch":false,"display":true,"type":"number","canBeUsedToMatch":true},{"id":"couponId","displayName":"couponId","required":false,"defaultMatch":false,"display":true,"type":"number","canBeUsedToMatch":true},{"id":"issuedBy","displayName":"issuedBy","required":true,"defaultMatch":false,"display":true,"type":"options","canBeUsedToMatch":true,"options":[{"name":"Admin","value":"Admin"},{"name":"Manual","value":"Manual"},{"name":"Url","value":"Url"},{"name":"Auto","value":"Auto"},{"name":"Calculate","value":"Calculate"}]},{"id":"customData","displayName":"customData","required":false,"defaultMatch":false,"display":true,"type":"object","canBeUsedToMatch":true,"removed":true},{"id":"note","displayName":"note","required":false,"defaultMatch":false,"display":true,"type":"string","canBeUsedToMatch":true,"removed":true},{"id":"referrel__","displayName":"referrel__","required":false,"defaultMatch":false,"display":true,"type":"string","canBeUsedToMatch":true,"removed":true},{"id":"createdAt","displayName":"createdAt","required":false,"defaultMatch":false,"display":true,"type":"dateTime","canBeUsedToMatch":true,"removed":true},{"id":"updatedAt","displayName":"updatedAt","required":false,"defaultMatch":false,"display":true,"type":"dateTime","canBeUsedToMatch":true,"removed":true}]},"options":{}},"id":"06251fe9-591a-47cf-b5fd-1843859c2f27","name":"Postgres2","type":"n8n-nodes-base.postgres","typeVersion":2.5,"position":[2060,-420],"credentials":{"postgres":{"id":"fWzctmu40cX0DjDn","name":"Postgres account"}}},{"parameters":{"content":"## 쿠폰 발급","height":197.2971876690102,"width":891.9548404542992},"id":"23109e76-d5fc-4e5d-995f-7bdedbc4ab24","name":"Sticky Note6","type":"n8n-nodes-base.stickyNote","typeVersion":1,"position":[1560,-460]},{"parameters":{"assignments":{"assignments":[{"id":"9aa6fbef-68a5-4f75-8110-762e5989bed3","name":"folderId","value":"1F9fddbWPY-5ofuO-5UemIbZosYd4vj3j","type":"string"},{"id":"ed6dd815-77ea-45c1-8e39-bff082a3750f","name":"markdownText","value":"={{ $json.fields['생성된_마크다운'] }}","type":"string"},{"id":"889288d8-57d3-429e-83fa-f04a08e0b311","name":"title","value":"={{ $('Update Airtable Markdown').item.json.fields['게시글_제목'][0] }}","type":"string"},{"id":"01bd5f7e-e91f-4f56-b918-c6fdcbc975fd","name":"writer","value":"={{ $('Update Airtable Markdown').item.json.fields['게시글_작성자'][0] }}","type":"string"},{"id":"3fbf8197-827b-40e2-8c2f-5cb32e5d4598","name":"write_at","value":"={{ $('Update Airtable Markdown').item.json.fields['게시글_작성일'][0].slice(0,10) }}","type":"string"},{"id":"4bb5487f-fa12-49d5-8ae9-e644151a7379","name":"url","value":"={{ $('Update Airtable Markdown').item.json.fields.url }}","type":"string"},{"id":"339a6980-cb85-4620-b706-d18e4be5c1d4","name":"interest","value":"={{ $('Webhook').item.json.body.interest }}","type":"string"},{"id":"eaf8f424-833c-42d6-997c-cbc67d0bd95e","name":"name","value":"={{ $('Webhook').item.json.body.name[0] }}","type":"string"}]},"options":{}},"id":"7f5faa6b-b343-4e45-ba26-2b691e260856","name":"Set Slide Creation Fields","type":"n8n-nodes-base.set","typeVersion":3.4,"position":[1620,-143],"notesInFlow":true,"notes":"슬라이드 생성을 위해 필요한 필드를 설정하는 노드\n\n"},{"parameters":{"method":"POST","url":"https://script.google.com/macros/s/AKfycbxj-aCvDbDiccZju6t5GWCneGoY6XFWaVhbKyXIPJJ-yAHCU7GFIXRvGMR7OJ-mnRauGA/exec","sendBody":true,"specifyBody":"json","jsonBody":"=[{{ JSON.stringify($json) }}]","options":{}},"id":"7ab851ab-4185-4d30-adba-dc742e7834bc","name":"Slide Creation API Call","type":"n8n-nodes-base.httpRequest","typeVersion":4.2,"position":[1820,-143],"executeOnce":false,"retryOnFail":false,"maxTries":5,"waitBetweenTries":5000,"notesInFlow":true,"onError":"continueRegularOutput","notes":"슬라이드 제작을 요청하기 위해 외부 API에 POST 요청을 보내는 노드\n\n"},{"parameters":{"operation":"share","fileId":{"__rl":true,"value":"={{ $json.presentation.url }}","mode":"url"},"permissionsUi":{"permissionsValues":{"role":"writer","type":"anyone"}},"options":{}},"id":"a90e47e1-0b21-4e2f-a168-7633012cb11c","name":"Google Drive Sharing","type":"n8n-nodes-base.googleDrive","typeVersion":3,"position":[2040,-143],"notesInFlow":true,"credentials":{"googleDriveOAuth2Api":{"id":"NWnrHyjTqPrRa3n7","name":"Google Drive account"}},"notes":"Google Drive에 생성된 슬라이드를 공유 설정하는 노드\n\n"},{"parameters":{"content":"## 구글 슬라이드 생성","height":323.54763699196485,"width":621.5874345549744},"id":"dd09254e-9778-40dc-99d7-92f80312844f","name":"Sticky Note7","type":"n8n-nodes-base.stickyNote","typeVersion":1,"position":[1580,-220]},{"parameters":{"endpoint":"={{ $vars.bettermode_end_point }}","requestFormat":"json","query":"=query {\n  spaceRoles(spaceId: {{ JSON.stringify($json.body[0].spaceId.id) }}) {\n    id\n    name\n    type\n    description\n  }\n}\n","variables":"=","responseFormat":"=json","headerParametersUi":{"parameter":[{"name":"={{ $vars.bettermode_client_id_key }}","value":"={{ $vars.bettermode_client_id_value }}"},{"name":"={{ $vars.bettermode_client_secret_key }}","value":"={{ $vars.bettermode_client_secret_value }}"}]}},"id":"c763308a-0705-4a7b-97c3-9ad402aa75e3","name":"getSpaceRole","type":"n8n-nodes-base.graphql","typeVersion":1,"position":[2380,0],"notesInFlow":true,"notes":"getSpaceRole은 space에 있는 role 데이터를 가져오기 위해 진행한다.\n\nrole의 id 값이 다 다르기 때문이다.\n\n이게 있어야 멤버를 특정 게시판에 참여시킬 수 있다."},{"parameters":{"jsCode":"// memberIds 배열 변환 로직\nconst memberIds = $('Webhook').first().json.body[0].memberId;\nconsole.log(memberIds);\n\n// 'getSpaceRole' 데이터에서 \"Member\" 역할을 찾아 roleId 추출\nconst spaceRoles = $('getSpaceRole').first().json.data.spaceRoles;\nconst memberRole = spaceRoles.find(role => role.name === 'Member');\nconst roleId = memberRole ? memberRole.id : null; // Member 역할이 없을 경우를 대비한 처리\n\n// memberIds 배열을 순회하며 roleId와 memberId로 이루어진 객체 배열 생성\nconst res = memberIds.map(id => ({\n    roleId: roleId,\n    memberId: id\n}));\n\nreturn { input: res };\n"},"id":"2bbfa4d0-58c5-4185-ad72-2aea9959ed18","name":"makeArrayId","type":"n8n-nodes-base.code","typeVersion":2,"position":[2600,0],"notes":"3. **멤버 ID와 역할 ID 배열 생성**: 멤버 ID와 역할 ID를 배열 형태로 변환하여 초대 준비를 완료합니다.\n"},{"parameters":{"endpoint":"={{ $vars.bettermode_end_point}}","requestFormat":"json","query":"mutation addSpaceMembers($spaceId: ID!, $input: [AddSpaceMemberInput!]!) { \n  addSpaceMembers(input: $input, spaceId: $spaceId) { \n    space { \n      id \n    } \n    member { \n      id \n      name \n    } \n  } \n}","variables":"={\n    \"spaceId\": \"{{ $node[\"Webhook\"].json[\"body\"][\"0\"][\"spaceId\"][\"id\"] }}\",\n    \"input\": {{ JSON.stringify($json.input) }}\n  }","headerParametersUi":{"parameter":[{"name":"={{ $vars.bettermode_client_id_key }}","value":"={{ $vars.bettermode_client_id_value }}"},{"name":"={{ $vars.bettermode_client_secret_key }}","value":"={{ $vars.bettermode_client_secret_value }}"}]}},"id":"1f19320b-ce81-4f9e-a162-b158f23801cc","name":"inviteMember","type":"n8n-nodes-base.graphql","typeVersion":1,"position":[2860,0],"notes":"4. **멤버 초대**: `inviteMember` 노드가 멤버들을 지정된 게시판에 초대합니다.\n"},{"parameters":{"endpoint":"={{ $vars.bettermode_end_point }}","requestFormat":"json","query":"=query {\n  spaceRoles(spaceId: {{ JSON.stringify($json.body[0].spaceId.id) }}) {\n    id\n    name\n    type\n    description\n  }\n}\n","variables":"=","responseFormat":"=json","headerParametersUi":{"parameter":[{"name":"={{ $vars.bettermode_client_id_key }}","value":"={{ $vars.bettermode_client_id_value }}"},{"name":"={{ $vars.bettermode_client_secret_key }}","value":"={{ $vars.bettermode_client_secret_value }}"}]}},"id":"be8e4c69-6f5c-4a12-be26-38bbb0fd5aff","name":"getSpaceRole1","type":"n8n-nodes-base.graphql","typeVersion":1,"position":[1580,-780],"notesInFlow":true,"notes":"getSpaceRole은 space에 있는 role 데이터를 가져오기 위해 진행한다.\n\nrole의 id 값이 다 다르기 때문이다.\n\n이게 있어야 멤버를 특정 게시판에 참여시킬 수 있다."},{"parameters":{"jsCode":"// memberIds 배열 변환 로직\nconst memberIds = $('Webhook').first().json.body[0].memberId;\nconsole.log(memberIds);\n\n// 'getSpaceRole' 데이터에서 \"Member\" 역할을 찾아 roleId 추출\nconst spaceRoles = $('getSpaceRole1').first().json.data.spaceRoles;\nconst memberRole = spaceRoles.find(role => role.name === 'Member');\nconst roleId = memberRole ? memberRole.id : null; // Member 역할이 없을 경우를 대비한 처리\n\n// memberIds 배열을 순회하며 roleId와 memberId로 이루어진 객체 배열 생성\nconst res = memberIds.map(id => ({\n    roleId: roleId,\n    memberId: id\n}));\n\nreturn { input: res };\n"},"id":"619c5736-9e3b-46e2-98b4-a66f443f8ce9","name":"makeArrayId1","type":"n8n-nodes-base.code","typeVersion":2,"position":[1800,-780],"notes":"3. **멤버 ID와 역할 ID 배열 생성**: 멤버 ID와 역할 ID를 배열 형태로 변환하여 초대 준비를 완료합니다.\n"},{"parameters":{"endpoint":"={{ $vars.bettermode_end_point}}","requestFormat":"json","query":"mutation addSpaceMembers($spaceId: ID!, $input: [AddSpaceMemberInput!]!) { \n  addSpaceMembers(input: $input, spaceId: $spaceId) { \n    space { \n      id \n    } \n    member { \n      id \n      name \n    } \n  } \n}","variables":"={\n    \"spaceId\": \"{{ $node[\"Webhook\"].json[\"body\"][\"0\"][\"spaceId\"][\"id\"] }}\",\n    \"input\": {{ JSON.stringify($json.input) }}\n  }","headerParametersUi":{"parameter":[{"name":"={{ $vars.bettermode_client_id_key }}","value":"={{ $vars.bettermode_client_id_value }}"},{"name":"={{ $vars.bettermode_client_secret_key }}","value":"={{ $vars.bettermode_client_secret_value }}"}]}},"id":"847cf46b-df52-4c60-b0fe-78a28faeecbd","name":"inviteMember1","type":"n8n-nodes-base.graphql","typeVersion":1,"position":[2060,-780],"notes":"4. **멤버 초대**: `inviteMember` 노드가 멤버들을 지정된 게시판에 초대합니다.\n"},{"parameters":{"content":"## graphql 로 Role 조회 및 게시판 초대","height":410,"width":863.046875},"id":"3c9a8c63-24ea-450a-a9e2-27048e198712","name":"Sticky Note8","type":"n8n-nodes-base.stickyNote","typeVersion":1,"position":[1520,-940]}],"connections":{"Code":{"main":[[{"node":"HTTP Request1","type":"main","index":0}]]},"Edit Fields2":{"main":[[{"node":"Execute Workflow1","type":"main","index":0}]]},"Code1":{"main":[[{"node":"HTTP Request","type":"main","index":0}]]},"Edit Fields1":{"main":[[{"node":"Execute Workflow","type":"main","index":0}]]},"Wait":{"main":[[{"node":"Airtable","type":"main","index":0}]]},"Execute Workflow":{"main":[[{"node":"Wait","type":"main","index":0}]]},"getZoomUrl":{"main":[[{"node":"sendHookZapier","type":"main","index":0}]]},"Edit Fields3":{"main":[[{"node":"Postgres2","type":"main","index":0}]]},"Set Slide Creation Fields":{"main":[[{"node":"Slide Creation API Call","type":"main","index":0}]]},"Slide Creation API Call":{"main":[[{"node":"Google Drive Sharing","type":"main","index":0}]]},"getSpaceRole":{"main":[[{"node":"makeArrayId","type":"main","index":0}]]},"makeArrayId":{"main":[[{"node":"inviteMember","type":"main","index":0}]]},"getSpaceRole1":{"main":[[{"node":"makeArrayId1","type":"main","index":0}]]},"makeArrayId1":{"main":[[{"node":"inviteMember1","type":"main","index":0}]]}},"settings":{"executionOrder":"v1"},"staticData":null,"meta":{"templateCredsSetupCompleted":true},"pinData":{"Edit Fields3":[{"json":{"id":34788}},{"json":{"id":34870}},{"json":{"id":34985}},{"json":{"id":35004}},{"json":{"id":35028}},{"json":{"id":35029}},{"json":{"id":35032}},{"json":{"id":35109}},{"json":{"id":35192}},{"json":{"id":35290}},{"json":{"id":35392}},{"json":{"id":35436}},{"json":{"id":35443}},{"json":{"id":35579}},{"json":{"id":35614}},{"json":{"id":35615}},{"json":{"id":35625}},{"json":{"id":35679}},{"json":{"id":35864}},{"json":{"id":36217}},{"json":{"id":36303}},{"json":{"id":36336}},{"json":{"id":36521}},{"json":{"id":36560}},{"json":{"id":38636}},{"json":{"id":42972}},{"json":{"id":43050}},{"json":{"id":44202}},{"json":{"id":45059}}]},"versionId":"2ef74c9a-1f70-4030-9346-f0c20b0afcfa","triggerCount":0,"tags":[]}